pghistory/__init__.py
pghistory/admin/__init__.py
pghistory/admin/apps.py
pghistory/admin/core.py
pghistory/admin/templates/admin/change_form_object_tools.html
pghistory/admin/templates/admin/change_list_object_tools.html
pghistory/admin/templates/pghistory_admin/events_change_list.html
pghistory/admin/templates/pghistory_admin/hidden_filter.html
pghistory/admin/templatetags/pghistory_admin.py
pghistory/apps.py
pghistory/checks.py
pghistory/config.py
pghistory/constants.py
pghistory/core.py
pghistory/deprecated.py
pghistory/middleware.py
pghistory/migrations/0001_initial.py
pghistory/migrations/0002_aggregateevent.py
pghistory/migrations/0003_auto_20201023_1636.py
pghistory/migrations/0004_auto_20220906_1625.py
pghistory/migrations/0005_events_middlewareevents.py
pghistory/migrations/__init__.py
pghistory/models.py
pghistory/runtime.py
pghistory/trigger.py
pghistory/utils.py
pghistory/version.py
baseapp_django_pghistory-2.8.2.dist-info/LICENSE
baseapp_django_pghistory-2.8.2.dist-info/METADATA
baseapp_django_pghistory-2.8.2.dist-info/WHEEL
baseapp_django_pghistory-2.8.2.dist-info/RECORD
