Metadata-Version: 2.1
Name: baseapp-django-pghistory
Version: 2.8.2
Summary: History tracking for Django and Postgres (updated for Baseapp)
Home-page: https://github.com/silverlogic/django-pghistory
License: BSD-3-Clause
Author: Wes Kendall
Requires-Python: >=3.7.0,<4
Classifier: Framework :: Django
Classifier: Framework :: Django :: 3.2
Classifier: Framework :: Django :: 4.0
Classifier: Framework :: Django :: 4.1
Classifier: Framework :: Django :: 4.2
Classifier: Intended Audience :: Developers
Classifier: License :: OSI Approved :: BSD License
Classifier: Operating System :: OS Independent
Classifier: Programming Language :: Python
Classifier: Programming Language :: Python :: 3
Classifier: Programming Language :: Python :: 3.7
Classifier: Programming Language :: Python :: 3.8
Classifier: Programming Language :: Python :: 3.9
Classifier: Programming Language :: Python :: 3.10
Classifier: Programming Language :: Python :: 3.11
Classifier: Programming Language :: Python :: 3 :: Only
Requires-Dist: django (>=2)
Requires-Dist: django-pgtrigger (>=4.7.0)
Requires-Dist: importlib_metadata (>=4) ; python_version >= "3.7" and python_version < "3.8"
Project-URL: Documentation, https://django-pghistory.readthedocs.io
Project-URL: Repository, https://github.com/silverlogic/django-pghistory
